django_app_tree/__init__.py
django_app_tree/__main__.py
django_app_tree/something.py
django_app_tree/management/commands/dependency_tree.py
django_app_tree/management/commands/pip_for_apps.py
django_app_tree/management/commands/template_graph.py
django_app_tree-0.1.0.dist-info/LICENSE.md
django_app_tree-0.1.0.dist-info/METADATA
django_app_tree-0.1.0.dist-info/WHEEL
django_app_tree-0.1.0.dist-info/entry_points.txt
django_app_tree-0.1.0.dist-info/top_level.txt
django_app_tree-0.1.0.dist-info/RECORD
