Metadata-Version: 2.1
Name: django-app-tree
Version: 0.1.0
Home-page: https://github.com/pragmaticindustries/django-app-tree
Author: pragmatic industries GmbH
Author-email: info@pragmaticindustries.de
Maintainer: pragmatic industries GmbH
Maintainer-email: info@pragmaticindustries.de
License: Apache License
Project-URL: Homepage, https://github.com/pragmaticindustries/django-app-tree
Platform: 
Classifier: Development Status :: 1 - Planning
Classifier: Intended Audience :: Developers
Classifier: Natural Language :: English
Classifier: License :: OSI Approved :: Apache Software License
Classifier: Programming Language :: Python :: 3.8
Classifier: Programming Language :: Python :: 3.9
Classifier: Programming Language :: Python :: 3.10
Classifier: Programming Language :: Python :: 3 :: Only
Classifier: Programming Language :: Python :: Implementation :: CPython
Requires-Python: >=3.8
License-File: LICENSE.md
Provides-Extra: dev
Requires-Dist: bandit (==1.7.1) ; extra == 'dev'
Requires-Dist: flake8 (==4.0.1) ; extra == 'dev'
Requires-Dist: flake8-builtins (==1.5.3) ; extra == 'dev'
Requires-Dist: flake8-docstrings (==1.6.0) ; extra == 'dev'
Requires-Dist: flake8-rst-docstrings (==0.2.5) ; extra == 'dev'
Requires-Dist: hypothesis (==6.35.1) ; extra == 'dev'
Requires-Dist: mypy (==0.931) ; extra == 'dev'
Requires-Dist: pep8-naming (==0.12.1) ; extra == 'dev'
Requires-Dist: pre-commit (==2.17.0) ; extra == 'dev'
Requires-Dist: pylint (==2.12.2) ; extra == 'dev'
Requires-Dist: types-setuptools (==57.4.7) ; extra == 'dev'
Provides-Extra: docs
Requires-Dist: sphinx (==4.4.0) ; extra == 'docs'
Provides-Extra: test
Requires-Dist: hypothesis (==6.35.1) ; extra == 'test'
Requires-Dist: pytest (==6.2.5) ; extra == 'test'
Requires-Dist: pytest-cov (==3.0.0) ; extra == 'test'
